LICENSE
LICENSE.txt
MANIFEST.in
README.md
setup.py
aws_lambda_utility.egg-info/PKG-INFO
aws_lambda_utility.egg-info/SOURCES.txt
aws_lambda_utility.egg-info/dependency_links.txt
aws_lambda_utility.egg-info/entry_points.txt
aws_lambda_utility.egg-info/requires.txt
aws_lambda_utility.egg-info/top_level.txt
lambdautility/__init__.py
lambdautility/__main__.py
lambdautility/conn/aws/Connection.py
lambdautility/conn/db/Connection.py
lambdautility/decoradores/Dec.py
lambdautility/utilities/Constants.py
lambdautility/utilities/DatesCommon.py
lambdautility/utilities/MakeResponse.py
lambdautility/utilities/Task.py
lambdautility/vo/ResponseVO.py