Metadata-Version: 2.1
Name: aws-lambda-utility
Version: 1.0.11
Summary: Contiene clases, funciones, constantes comunes para proyectos aws
Home-page: https://github.com/juanfcosanz/python_package.git
Author: @jfsanz
Author-email: dolgasanz@gmail.com
License: GPLv3+
Keywords: aws,utilities
Platform: UNKNOWN
Classifier: Development Status :: 3 - Alpha
Classifier: Intended Audience :: Developers
Classifier: Topic :: Software Development :: Build Tools
Classifier: License :: OSI Approved :: GNU General Public License v3 or later (GPLv3+)
Classifier: License :: Other/Proprietary License
Classifier: Programming Language :: Python :: 3.6
Classifier: Operating System :: OS Independent
License-File: LICENSE
License-File: LICENSE.txt
